stmtools/__init__.py
stmtools/_io.py
stmtools/metadata.py
stmtools/stm.py
stmtools/utils.py
stmtools-0.1.4.dist-info/LICENSE
stmtools-0.1.4.dist-info/METADATA
stmtools-0.1.4.dist-info/WHEEL
stmtools-0.1.4.dist-info/top_level.txt
stmtools-0.1.4.dist-info/RECORD
