Metadata-Version: 2.1
Name: stmtools
Version: 0.1.4
Summary: space-time matrix for PS-InSAR application
Author: Fakhereh Alidoost, Pranav Chandramouli, Meiert Willem Grootes, Francesco Nattino, Thijs van Lankveld, Freek van Leijen
Author-email: Ou Ku <o.ku@esciencecenter.nl>
License:                                  Apache License
Project-URL: repository, https://github.com/TUDelftGeodesy/stmtools
Project-URL: doi, https://doi.org/10.5281/zenodo.7717112
Project-URL: documentation, https://tudelftgeodesy.github.io/stmtools/
Project-URL: changelog, https://tudelftgeodesy.github.io/stmtools/CHANGELOG/
Keywords: stm,sar,insar,space-time,psi
Classifier: Development Status :: 3 - Alpha
Classifier: Intended Audience :: Developers
Classifier: License :: OSI Approved :: Apache Software License
Classifier: Natural Language :: English
Classifier: Programming Language :: Python :: 3.10
Classifier: Programming Language :: Python :: 3.11
Classifier: Programming Language :: Python :: 3.12
Requires-Python: >=3.10
License-File: LICENSE
Requires-Dist: dask[complete]
Requires-Dist: xarray[io]
Requires-Dist: numpy
Requires-Dist: rasterio
Requires-Dist: geopandas
Requires-Dist: affine
Requires-Dist: zarr
Requires-Dist: distributed
Requires-Dist: pymorton
Provides-Extra: dev
Requires-Dist: pytest; extra == "dev"
Requires-Dist: pytest-cov; extra == "dev"
Requires-Dist: pycodestyle; extra == "dev"
Requires-Dist: ruff; extra == "dev"
Requires-Dist: pre-commit; extra == "dev"
Provides-Extra: docs
Requires-Dist: mkdocs; extra == "docs"
Requires-Dist: mkdocs-material; extra == "docs"
Requires-Dist: mkdocs-jupyter; extra == "docs"
Requires-Dist: mkdocstrings[python]; extra == "docs"
Requires-Dist: mkdocs-gen-files; extra == "docs"
Provides-Extra: demo
Requires-Dist: jupyterlab; extra == "demo"
Requires-Dist: matplotlib; extra == "demo"
